polars_greeks-0.1.1.dist-info/METADATA
polars_greeks-0.1.1.dist-info/WHEEL
polars_greeks/__init__.py
polars_greeks/_internal.cpython-310-x86_64-linux-gnu.so
polars_greeks/functions.py
polars_greeks-0.1.1.dist-info/RECORD
