Metadata-Version: 2.4
Name: polars-greeks
Version: 0.1.1
Classifier: Development Status :: 4 - Beta
Classifier: Intended Audience :: Developers
Classifier: Intended Audience :: Financial and Insurance Industry
Classifier: License :: OSI Approved :: MIT License
Classifier: Programming Language :: Python :: 3
Classifier: Programming Language :: Python :: 3.8
Classifier: Programming Language :: Python :: 3.9
Classifier: Programming Language :: Python :: 3.10
Classifier: Programming Language :: Python :: 3.11
Classifier: Programming Language :: Python :: 3.12
Classifier: Programming Language :: Rust
Classifier: Topic :: Office/Business :: Financial
Classifier: Topic :: Scientific/Engineering :: Mathematics
Classifier: Operating System :: OS Independent
Requires-Dist: polars>=0.20.0
Requires-Dist: pytest>=6.0 ; extra == 'test'
Requires-Dist: numpy>=1.20.0 ; extra == 'test'
Provides-Extra: test
Summary: High-performance Black-Scholes options pricing and Greeks calculation plugin for Polars
Keywords: polars,options,black-scholes,greeks,finance,quantitative,rust
Author: derek.jiao
License: MIT
Requires-Python: >=3.8
Project-URL: Homepage, https://github.com/jiaojing/polars-greeks
Project-URL: Repository, https://github.com/jiaojing/polars-greeks
Project-URL: Issues, https://github.com/jiaojing/polars-greeks/issues
